geodb_rs-0.1.5.dist-info/METADATA
geodb_rs-0.1.5.dist-info/WHEEL
geodb_rs/__init__.py
geodb_rs/geodb_rs.pyd
geodb_rs_data/geodb.flat.comp.blobs.bin
geodb_rs-0.1.5.dist-info/RECORD
