Metadata-Version: 2.4
Name: geodb-rs
Version: 0.1.5
Classifier: Programming Language :: Python
Classifier: Programming Language :: Python :: 3
Classifier: Programming Language :: Python :: 3 :: Only
Classifier: Programming Language :: Rust
Classifier: Operating System :: OS Independent
Summary: Python bindings for geodb-core
Home-Page: https://github.com/holg/geodb-rs
Author: Holger Trahe
License: MIT
Requires-Python: >=3.8
